python_analyst_utils/__init__.py
python_analyst_utils/csv_management/__init__.py
python_analyst_utils/csv_management/csv_manager.py
python_analyst_utils/date_management/__init__.py
python_analyst_utils/date_management/date_manager.py
python_analyst_utils/excel_management/__init__.py
python_analyst_utils/excel_management/excel_manager.py
python_analyst_utils/file_management/__init__.py
python_analyst_utils/file_management/file_storage_manager.py
python_analyst_utils/pandas_management/__init__.py
python_analyst_utils/pandas_management/pandas_transformation_helper.py
python_analyst_utils/pandas_management/helpers/__init__.py
python_analyst_utils/pandas_management/helpers/pandas_cleaning_helper.py
python_analyst_utils/pandas_management/helpers/pandas_column_helper.py
python_analyst_utils/pandas_management/helpers/pandas_content_helper.py
python_analyst_utils/pandas_management/helpers/pandas_diagnostic_helper.py
python_analyst_utils/pandas_management/helpers/pandas_merge_helper.py
python_analyst_utils/pandas_management/helpers/pandas_type_helper.py
tests/__init__.py
tests/test_csv_source_helper.py
tests/test_date_manager.py
tests/test_excel_manager.py
tests/test_file_storage_manager.py
tests/test_pandas_transformation_helper.py
python_analyst_utility-0.1.8.dist-info/LICENSE
python_analyst_utility-0.1.8.dist-info/METADATA
python_analyst_utility-0.1.8.dist-info/WHEEL
python_analyst_utility-0.1.8.dist-info/top_level.txt
python_analyst_utility-0.1.8.dist-info/RECORD
